jd_cps_sdk/__init__.py
jd_cps_sdk-0.0.1.dist-info/LICENSE
jd_cps_sdk-0.0.1.dist-info/METADATA
jd_cps_sdk-0.0.1.dist-info/WHEEL
jd_cps_sdk-0.0.1.dist-info/top_level.txt
jd_cps_sdk-0.0.1.dist-info/RECORD
