Metadata-Version: 2.1
Name: jd-cps-sdk
Version: 0.0.1
Summary: jd cps sdk
Home-page: https://github.com/luckylu/jd_cps_sdk
Author: Michael
Author-email: kobelu1990@gmail.com
License: UNKNOWN
Platform: UNKNOWN
Classifier: Programming Language :: Python :: 3
Classifier: License :: OSI Approved :: MIT License
Classifier: Operating System :: OS Independent
Requires-Python: >=3.6
